{
    "помогают ему":{}, 
    "мешает президенту Путину":{}, 
    "вредит здоровью":{}, 
    "советуешь родителям":{}, 
    "приказал командиру":{},
	"верим американцам":{}, 
    "желаю удачи":{}, 
    "боюсь собак":{}, 
    "занималась поисками":{}, 
    "увлекался химией":{}, 
    "руководят преступными сообществами":{},
	"любоваться красивыми растениями":{}, 
    "восхищаешься игрой":{}, 
    "пользовалась большой популярностью":{}, 
    "болел малярией":{}, 
    "интересуется датским":{}, 
    "наслаждались дождём":{},
	"наслаждались дождем":{}


}